pytest_starlite_saqlalchemy/__init__.py
pytest_starlite_saqlalchemy/plugin.py
starlite_saqlalchemy/__init__.py
starlite_saqlalchemy/cache.py
starlite_saqlalchemy/compression.py
starlite_saqlalchemy/constants.py
starlite_saqlalchemy/db/__init__.py
starlite_saqlalchemy/db/orm.py
starlite_saqlalchemy/dependencies.py
starlite_saqlalchemy/dto/__init__.py
starlite_saqlalchemy/dto/from_mapped.py
starlite_saqlalchemy/dto/types.py
starlite_saqlalchemy/dto/utils.py
starlite_saqlalchemy/endpoint_decorator.py
starlite_saqlalchemy/exceptions.py
starlite_saqlalchemy/health.py
starlite_saqlalchemy/http.py
starlite_saqlalchemy/init_plugin.py
starlite_saqlalchemy/lifespan.py
starlite_saqlalchemy/log/__init__.py
starlite_saqlalchemy/log/controller.py
starlite_saqlalchemy/log/utils.py
starlite_saqlalchemy/log/worker.py
starlite_saqlalchemy/openapi.py
starlite_saqlalchemy/py.typed
starlite_saqlalchemy/redis.py
starlite_saqlalchemy/repository/__init__.py
starlite_saqlalchemy/repository/abc.py
starlite_saqlalchemy/repository/filters.py
starlite_saqlalchemy/repository/sqlalchemy.py
starlite_saqlalchemy/repository/types.py
starlite_saqlalchemy/scripts.py
starlite_saqlalchemy/sentry.py
starlite_saqlalchemy/service/__init__.py
starlite_saqlalchemy/service/generic.py
starlite_saqlalchemy/service/sqlalchemy.py
starlite_saqlalchemy/settings.py
starlite_saqlalchemy/sqlalchemy_plugin.py
starlite_saqlalchemy/static/starlite-favicon.ico
starlite_saqlalchemy/testing/__init__.py
starlite_saqlalchemy/testing/controller_test.py
starlite_saqlalchemy/testing/generic_mock_repository.py
starlite_saqlalchemy/testing/modify_settings.py
starlite_saqlalchemy/type_encoders.py
starlite_saqlalchemy/utils.py
starlite_saqlalchemy/worker.py
starlite_saqlalchemy-0.30.0.dist-info/LICENSE
starlite_saqlalchemy-0.30.0.dist-info/METADATA
starlite_saqlalchemy-0.30.0.dist-info/WHEEL
starlite_saqlalchemy-0.30.0.dist-info/entry_points.txt
starlite_saqlalchemy-0.30.0.dist-info/RECORD
