Metadata-Version: 2.1
Name: starlite-saqlalchemy
Version: 0.30.0
Summary: Starlite config plugin with SAQ and SQLAlchemy boilerplate
Home-page: https://github.com/topsport-com-au/starlite-saqlalchemy
License: MIT
Keywords: api,rest,http,asgi,starlite,saq,sqlalchemy,plugin,python
Author: Peter Schutt
Author-email: peter.github@proton.me
Requires-Python: >=3.10,<4.0
Classifier: Development Status :: 4 - Beta
Classifier: Environment :: Plugins
Classifier: Framework :: Pytest
Classifier: Intended Audience :: Developers
Classifier: License :: OSI Approved :: MIT License
Classifier: Natural Language :: English
Classifier: Operating System :: OS Independent
Classifier: Programming Language :: Python :: 3
Classifier: Programming Language :: Python :: 3.10
Classifier: Programming Language :: Python :: 3.11
Classifier: Topic :: Internet :: WWW/HTTP
Classifier: Topic :: Software Development
Classifier: Topic :: System :: Installation/Setup
Provides-Extra: all
Provides-Extra: cache
Provides-Extra: sentry
Provides-Extra: sqlalchemy
Provides-Extra: worker
Requires-Dist: asyncpg
Requires-Dist: hiredis ; extra == "cache" or extra == "worker" or extra == "all"
Requires-Dist: httpx
Requires-Dist: msgspec
Requires-Dist: pydantic
Requires-Dist: python-dotenv
Requires-Dist: redis ; extra == "cache" or extra == "all"
Requires-Dist: saq (>=0.9.1,<0.10.0) ; extra == "worker" or extra == "all"
Requires-Dist: sentry-sdk ; extra == "sentry" or extra == "all"
Requires-Dist: sqlalchemy (>=2.0,<3.0) ; extra == "sqlalchemy" or extra == "all"
Requires-Dist: starlite (>=1.51.2,<1.52.0)
Requires-Dist: structlog (>=22.2.0)
Requires-Dist: tenacity
Requires-Dist: uvicorn
Requires-Dist: uvloop
Project-URL: Bugs, https://github.com/topsport-com-au/starlite-saqlalchemy/issues
Project-URL: GitHub, https://github.com/topsport-com-au
Project-URL: Repository, https://github.com/topsport-com-au/starlite-saqlalchemy
